wembed.cpython-38-x86_64-linux-gnu.so
wembed.libs/libgomp-a34b3233.so.1.0.0
wembed-0.0.3.dist-info/WHEEL
wembed-0.0.3.dist-info/RECORD
wembed-0.0.3.dist-info/METADATA
wembed-0.0.3.dist-info/licenses/LICENSE
