Metadata-Version: 2.1
Name: wembed
Version: 0.0.3
Summary: WEmbed python bindings to calculate weighted node embeddings
Author-Email: Jean-Pierre von der Heydt <heydt@kit.edu>, Nikolai Maas <nikolai.maas@kit.edu>
License: MIT License
Classifier: License :: OSI Approved :: MIT License
Classifier: Programming Language :: Python :: 3
Classifier: Programming Language :: C++
Requires-Python: >=3.7
